{
  "$schema": "./theme.schema.json",
  "name": "Synergy",
  "id": "synergy",
  "light": {
    "seeds": {
      "neutral": "#86868B",
      "primary": "#007AFF",
      "success": "#28CD41",
      "warning": "#FF9500",
      "error": "#FF3B30",
      "info": "#5856D6",
      "interactive": "#007AFF",
      "diffAdd": "#28CD41",
      "diffDelete": "#FF3B30"
    },
    "overrides": {
      "background-base": "#FFFFFF",
      "background-weak": "#F5F5F7",
      "background-strong": "#FFFFFF",
      "background-stronger": "#FFFFFF",

      "surface-float-base": "#1D1D1F",
      "surface-float-base-hover": "#2C2C2E",

      "button-secondary-base": "#F5F5F7",
      "button-secondary-hover": "#E8E8ED",

      "border-color": "#FFFFFF",

      "syntax-comment": "var(--text-weaker)",
      "syntax-regexp": "var(--text-base)",
      "syntax-string": "#C41A16",
      "syntax-keyword": "#9B2393",
      "syntax-primitive": "#1C00CF",
      "syntax-operator": "var(--text-base)",
      "syntax-variable": "var(--text-strong)",
      "syntax-property": "#326D74",
      "syntax-type": "#0B4F79",
      "syntax-constant": "#1C00CF",
      "syntax-punctuation": "var(--text-base)",
      "syntax-object": "var(--text-strong)",
      "syntax-info": "#0B4F79",
      "syntax-diff-unknown": "#FF3B30",

      "markdown-heading": "#1D1D1F",
      "markdown-text": "#1D1D1F",
      "markdown-link": "#007AFF",
      "markdown-link-text": "#0B4F79",
      "markdown-code": "#C41A16",
      "markdown-block-quote": "#86868B",
      "markdown-emph": "#9B2393",
      "markdown-strong": "#1D1D1F",
      "markdown-horizontal-rule": "#D1D1D6",
      "markdown-list-item": "#007AFF",
      "markdown-list-enumeration": "#0B4F79",
      "markdown-image": "#007AFF",
      "markdown-image-text": "#0B4F79",
      "markdown-code-block": "#1D1D1F",

      "avatar-background-pink": "#FFF0F5",
      "avatar-background-mint": "#E5FBF8",
      "avatar-background-orange": "#FFF3E6",
      "avatar-background-purple": "#F6F0FE",
      "avatar-background-cyan": "#ECF4FF",
      "avatar-background-lime": "#ECFAE6",
      "avatar-text-pink": "#FF2D55",
      "avatar-text-mint": "#00C7BE",
      "avatar-text-orange": "#FF9500",
      "avatar-text-purple": "#AF52DE",
      "avatar-text-cyan": "#007AFF",
      "avatar-text-lime": "#28CD41"
    }
  },
  "dark": {
    "seeds": {
      "neutral": "#86868B",
      "primary": "#0A84FF",
      "success": "#32D74B",
      "warning": "#FFD60A",
      "error": "#FF453A",
      "info": "#5E5CE6",
      "interactive": "#0A84FF",
      "diffAdd": "#32D74B",
      "diffDelete": "#FF453A"
    },
    "overrides": {
      "background-base": "#000000",
      "background-weak": "#1C1C1E",
      "background-strong": "#000000",
      "background-stronger": "#0A0A0C",

      "surface-float-base": "#1C1C1E",
      "surface-float-base-hover": "#2C2C2E",

      "button-secondary-base": "#1C1C1E",
      "button-secondary-hover": "#2C2C2E",

      "border-color": "#000000",

      "syntax-comment": "var(--text-weaker)",
      "syntax-regexp": "var(--text-base)",
      "syntax-string": "#FF8170",
      "syntax-keyword": "#FF7AB2",
      "syntax-primitive": "#D0A8FF",
      "syntax-operator": "var(--text-weak)",
      "syntax-variable": "var(--text-strong)",
      "syntax-property": "#ACF2E4",
      "syntax-type": "#6BDFFF",
      "syntax-constant": "#D0BF69",
      "syntax-punctuation": "var(--text-weak)",
      "syntax-object": "var(--text-strong)",
      "syntax-info": "#6BDFFF",
      "syntax-diff-unknown": "#FF453A",

      "markdown-heading": "#F5F5F7",
      "markdown-text": "#F5F5F7",
      "markdown-link": "#0A84FF",
      "markdown-link-text": "#6BDFFF",
      "markdown-code": "#FF8170",
      "markdown-block-quote": "#98989D",
      "markdown-emph": "#FF7AB2",
      "markdown-strong": "#F5F5F7",
      "markdown-horizontal-rule": "#48484A",
      "markdown-list-item": "#0A84FF",
      "markdown-list-enumeration": "#6BDFFF",
      "markdown-image": "#0A84FF",
      "markdown-image-text": "#6BDFFF",
      "markdown-code-block": "#F5F5F7",

      "avatar-background-pink": "#3A1325",
      "avatar-background-mint": "#0A2E2C",
      "avatar-background-orange": "#3A2208",
      "avatar-background-purple": "#2A1541",
      "avatar-background-cyan": "#0A1E3A",
      "avatar-background-lime": "#1A2E0E",
      "avatar-text-pink": "#FF375F",
      "avatar-text-mint": "#63E6E2",
      "avatar-text-orange": "#FF9F0A",
      "avatar-text-purple": "#BF5AF2",
      "avatar-text-cyan": "#0A84FF",
      "avatar-text-lime": "#32D74B"
    }
  }
}
