{
  "$schema": "./theme.schema.json",
  "name": "Synergy",
  "id": "synergy",
  "light": {
    "seeds": {
      "neutral": "#6B6B6B",
      "primary": "#3B82F6",
      "success": "#22C55E",
      "warning": "#F59E0B",
      "error": "#EF4444",
      "info": "#3B82F6",
      "interactive": "#3B82F6",
      "diffAdd": "#22C55E",
      "diffDelete": "#EF4444"
    },
    "overrides": {
      "background-base": "#FAFAFA",
      "background-weak": "#F3F4F6",
      "background-strong": "#F7F7F7",
      "background-stronger": "#FCFCFC",
      "surface-base": "#FFFFFF",
      "surface-base-hover": "#F8F8F8",
      "surface-base-active": "#F0F0F0",
      "surface-inset-base": "#F3F4F6",
      "surface-inset-base-hover": "#EBECEE",
      "surface-inset-strong": "#E5E7EB",
      "surface-inset-strong-hover": "#D1D5DB",
      "surface-raised-base": "#FFFFFF",
      "surface-raised-base-hover": "#F9FAFB",
      "surface-raised-base-active": "#F3F4F6",
      "surface-raised-strong": "#FFFFFF",
      "surface-raised-strong-hover": "#FDFDFD",
      "surface-raised-stronger": "#FFFFFF",
      "surface-raised-stronger-hover": "#FDFDFD",
      "surface-raised-stronger-non-alpha": "#FFFFFF",
      "surface-float-base": "#1F2937",
      "surface-float-base-hover": "#374151",
      "surface-brand-base": "#3B82F6",
      "surface-brand-hover": "#2563EB",
      "button-secondary-base": "#F3F4F6",
      "button-secondary-hover": "#E5E7EB",
      "text-base": "#111827",
      "text-weak": "#374151",
      "text-weaker": "#6B7280",
      "text-subtle": "#9CA3AF",
      "text-strong": "#030712",
      "text-interactive-base": "#2563EB",
      "icon-base": "#1F2937",
      "icon-hover": "#030712",
      "icon-weak-base": "#4B5563",
      "icon-weak-hover": "#111827",
      "text-on-interactive-base": "#FFFFFF",
      "border-color": "#FFFFFF",
      "border-base": "rgba(17, 24, 39, 0.14)",
      "border-weak-base": "rgba(17, 24, 39, 0.10)",
      "border-weaker-base": "rgba(17, 24, 39, 0.06)",
      "border-strong-base": "rgba(17, 24, 39, 0.20)",
      "border-selected": "rgba(59, 130, 246, 0.85)",
      "border-interactive-base": "#3B82F6",
      "markdown-heading": "#111827",
      "markdown-text": "#111827",
      "markdown-link": "#3B82F6",
      "markdown-link-text": "#2563EB",
      "markdown-code": "#374151",
      "markdown-block-quote": "#374151",
      "markdown-emph": "#374151",
      "markdown-strong": "#111827",
      "markdown-horizontal-rule": "#E5E7EB",
      "markdown-list-item": "#3B82F6",
      "markdown-list-enumeration": "#2563EB",
      "markdown-image": "#3B82F6",
      "markdown-image-text": "#2563EB",
      "markdown-code-block": "#111827",
      "syntax-comment": "var(--text-weaker)",
      "syntax-regexp": "var(--text-base)",
      "syntax-string": "#374151",
      "syntax-keyword": "#6B7280",
      "syntax-primitive": "#3B82F6",
      "syntax-operator": "var(--text-base)",
      "syntax-variable": "var(--text-strong)",
      "syntax-property": "#2563EB",
      "syntax-type": "#374151",
      "syntax-constant": "#3B82F6",
      "syntax-punctuation": "var(--text-base)",
      "syntax-object": "var(--text-strong)",
      "syntax-info": "#2563EB",
      "syntax-diff-unknown": "#EF4444",
      "avatar-background-pink": "#FFF1F3",
      "avatar-background-mint": "#EAF8F2",
      "avatar-background-orange": "#FFF3E8",
      "avatar-background-purple": "#F6F0FB",
      "avatar-background-cyan": "#EAF7F7",
      "avatar-background-lime": "#EFF7E6",
      "avatar-text-pink": "#B84A6B",
      "avatar-text-mint": "#1F8A5B",
      "avatar-text-orange": "#B7791F",
      "avatar-text-purple": "#7C4BA3",
      "avatar-text-cyan": "#286AA8",
      "avatar-text-lime": "#5D770D"
    }
  },
  "dark": {
    "seeds": {
      "neutral": "#A0A0A0",
      "primary": "#3B82F6",
      "success": "#22C55E",
      "warning": "#F59E0B",
      "error": "#EF4444",
      "info": "#60A5FA",
      "interactive": "#3B82F6",
      "diffAdd": "#22C55E",
      "diffDelete": "#EF4444"
    },
    "overrides": {
      "background-base": "#18181B",
      "background-weak": "#1C1C1F",
      "background-strong": "#18181B",
      "background-stronger": "#18181B",
      "surface-base": "#202124",
      "surface-base-hover": "#27272A",
      "surface-base-active": "#2F3034",
      "surface-inset-base": "#242529",
      "surface-inset-base-hover": "#2A2B30",
      "surface-inset-strong": "#2B2C31",
      "surface-inset-strong-hover": "#33343A",
      "surface-raised-base": "#27272A",
      "surface-raised-base-hover": "#2F3034",
      "surface-raised-base-active": "#35363A",
      "surface-raised-strong": "#2F3034",
      "surface-raised-strong-hover": "#35363A",
      "surface-raised-stronger": "#35363A",
      "surface-raised-stronger-hover": "#3A3B3F",
      "surface-raised-stronger-non-alpha": "#27272A",
      "surface-float-base": "#202124",
      "surface-float-base-hover": "#27272A",
      "surface-brand-base": "#3B82F6",
      "surface-brand-hover": "#2563EB",
      "button-secondary-base": "#27272A",
      "button-secondary-hover": "#2F3034",
      "text-base": "#F4F4F5",
      "text-weak": "#D4D4D8",
      "text-weaker": "#A1A1AA",
      "text-subtle": "#71717A",
      "text-strong": "#FAFAFA",
      "text-interactive-base": "#60A5FA",
      "icon-base": "#E4E4E7",
      "icon-hover": "#FAFAFA",
      "icon-weak-base": "#C5C5CC",
      "icon-weak-hover": "#F4F4F5",
      "text-on-interactive-base": "#FAFAFA",
      "border-color": "#18181B",
      "border-base": "rgba(244, 244, 245, 0.10)",
      "border-weak-base": "rgba(244, 244, 245, 0.08)",
      "border-weaker-base": "rgba(244, 244, 245, 0.05)",
      "border-strong-base": "rgba(244, 244, 245, 0.14)",
      "border-selected": "rgba(96, 165, 250, 0.85)",
      "border-interactive-base": "#3B82F6",
      "markdown-heading": "#F4F4F5",
      "markdown-text": "#F4F4F5",
      "markdown-link": "#60A5FA",
      "markdown-link-text": "#60A5FA",
      "markdown-code": "#D4D4D8",
      "markdown-block-quote": "#D4D4D8",
      "markdown-emph": "#D4D4D8",
      "markdown-strong": "#FAFAFA",
      "markdown-horizontal-rule": "#3F3F46",
      "markdown-list-item": "#60A5FA",
      "markdown-list-enumeration": "#60A5FA",
      "markdown-image": "#60A5FA",
      "markdown-image-text": "#60A5FA",
      "markdown-code-block": "#F4F4F5",
      "syntax-comment": "var(--text-weaker)",
      "syntax-regexp": "var(--text-base)",
      "syntax-string": "#D4D4D8",
      "syntax-keyword": "#A1A1AA",
      "syntax-primitive": "#60A5FA",
      "syntax-operator": "var(--text-weak)",
      "syntax-variable": "var(--text-strong)",
      "syntax-property": "#60A5FA",
      "syntax-type": "#D4D4D8",
      "syntax-constant": "#60A5FA",
      "syntax-punctuation": "var(--text-weak)",
      "syntax-object": "var(--text-strong)",
      "syntax-info": "#60A5FA",
      "syntax-diff-unknown": "#EF4444",
      "avatar-background-pink": "#3B1F2E",
      "avatar-background-mint": "#133329",
      "avatar-background-orange": "#3E2919",
      "avatar-background-purple": "#332347",
      "avatar-background-cyan": "#163338",
      "avatar-background-lime": "#243317",
      "avatar-text-pink": "#E58CAC",
      "avatar-text-mint": "#5FD39A",
      "avatar-text-orange": "#E0A85D",
      "avatar-text-purple": "#BC8EEA",
      "avatar-text-cyan": "#6FC9C9",
      "avatar-text-lime": "#B5D46D"
    }
  }
}
